neoclient/__init__.py
neoclient/annotations.py
neoclient/api.py
neoclient/auths.py
neoclient/client.py
neoclient/composition.py
neoclient/constants.py
neoclient/consumers.py
neoclient/converters.py
neoclient/decorators/__init__.py
neoclient/decorators/_headers.py
neoclient/decorators/api.py
neoclient/decorators/auth.py
neoclient/decorators/client.py
neoclient/decorators/common.py
neoclient/decorators/middleware.py
neoclient/decorators/operation.py
neoclient/decorators/request.py
neoclient/decorators/response.py
neoclient/decorators/service.py
neoclient/decorators/utils.py
neoclient/defaults.py
neoclient/dependence.py
neoclient/dependencies/__init__.py
neoclient/dependencies/_core.py
neoclient/dependencies/_headers.py
neoclient/enums.py
neoclient/errors.py
neoclient/middlewares.py
neoclient/models.py
neoclient/operation.py
neoclient/param_functions.py
neoclient/param_functions.pyi
neoclient/params.py
neoclient/py.typed
neoclient/resolution.py
neoclient/resolvers.py
neoclient/sentinels.py
neoclient/services.py
neoclient/specification.py
neoclient/types.py
neoclient/typing.py
neoclient/utils.py
neoclient/validation.py
neoclient-0.1.55.dist-info/LICENSE
neoclient-0.1.55.dist-info/METADATA
neoclient-0.1.55.dist-info/WHEEL
neoclient-0.1.55.dist-info/RECORD
